user_agent_parser/__init__.py
user_agent_parser/constants.py
user_agent_parser/parser.py
user_agent_parser-0.1.6.dist-info/LICENSE
user_agent_parser-0.1.6.dist-info/METADATA
user_agent_parser-0.1.6.dist-info/WHEEL
user_agent_parser-0.1.6.dist-info/RECORD
