Metadata-Version: 2.3
Name: user-agent-parser
Version: 0.1.6
Summary: Python 3 library to parse User-Agent strings and detect browser, OS and device details
License: MIT
Keywords: user agent,user-agent parser,ua parser,browser detection,device detection,python,http,analytics
Author: Purushot14
Author-email: prakash.purushoth@gmail.com
Requires-Python: >=3.8
Classifier: Environment :: Web Environment
Classifier: Intended Audience :: Developers
Classifier: License :: OSI Approved :: MIT License
Classifier: Operating System :: OS Independent
Classifier: Programming Language :: Python :: 3
Classifier: Programming Language :: Python :: 3.8
Classifier: Programming Language :: Python :: 3.9
Classifier: Programming Language :: Python :: 3.10
Classifier: Programming Language :: Python :: 3.11
Classifier: Programming Language :: Python :: 3.12
Classifier: Programming Language :: Python :: 3.13
Classifier: Programming Language :: Python :: 3 :: Only
Classifier: Topic :: Internet :: WWW/HTTP
Classifier: Topic :: Software Development :: Libraries :: Python Modules
Project-URL: Homepage, https://github.com/Purushot14/user-agent-parser
Project-URL: Repository, https://github.com/Purushot14/user-agent-parser
